README.md
ptimer.py
setup.py
ptimer.egg-info/PKG-INFO
ptimer.egg-info/SOURCES.txt
ptimer.egg-info/dependency_links.txt
ptimer.egg-info/top_level.txt